tabular_hypernet/__init__.py
tabular_hypernet/hypernetwork.py
tabular_hypernet/interfaces.py
tabular_hypernet/modules.py
tabular_hypernet/training_utils.py
tabular_hypernet/mask_design/__init__.py
tabular_hypernet/mask_design/feature_selection.py
tabular_hypernet-0.1.0.dist-info/METADATA
tabular_hypernet-0.1.0.dist-info/WHEEL
tabular_hypernet-0.1.0.dist-info/top_level.txt
tabular_hypernet-0.1.0.dist-info/RECORD
